civiclens/__init__.py
civiclens/cli.py
civiclens/data.py
civiclens/demo.py
civiclens/llm.py
civiclens/utils.py
civiclens/weather.py
civiclens-0.5.0.dist-info/METADATA
civiclens-0.5.0.dist-info/WHEEL
civiclens-0.5.0.dist-info/entry_points.txt
civiclens-0.5.0.dist-info/top_level.txt
civiclens-0.5.0.dist-info/RECORD
