Metadata-Version: 2.4
Name: civiclens
Version: 0.5.0
Summary: CivicLens AI – civic education and executive document analysis
Author-email: Theophilus Siameh <theodondre@gmail.com>
Requires-Python: >=3.10
Requires-Dist: argparse>=1.4.0
Requires-Dist: httpx>=0.28.1
Requires-Dist: loguru>=0.7.3
Requires-Dist: requests>=2.32.5
Requires-Dist: rich>=14.2.0
